LICENSE
MANIFEST.in
README.md
setup.py
DataStructure/CounterHashMap.c
DataStructure/CounterHashMap.pxd
DataStructure/CounterHashMap.pyx
DataStructure/Stack.c
DataStructure/Stack.pxd
DataStructure/Stack.pyx
DataStructure/__init__.py
DataStructure/Cache/LRUCache.c
DataStructure/Cache/LRUCache.pxd
DataStructure/Cache/LRUCache.pyx
DataStructure/Cache/__init__.py
DataStructure/Heap/Heap.c
DataStructure/Heap/Heap.pxd
DataStructure/Heap/Heap.pyx
DataStructure/Heap/HeapNode.c
DataStructure/Heap/HeapNode.pxd
DataStructure/Heap/HeapNode.pyx
DataStructure/Heap/MaxHeap.c
DataStructure/Heap/MaxHeap.pxd
DataStructure/Heap/MaxHeap.pyx
DataStructure/Heap/MinHeap.c
DataStructure/Heap/MinHeap.pxd
DataStructure/Heap/MinHeap.pyx
DataStructure/Heap/__init__.py
DataStructure/Tree/AvlTree.c
DataStructure/Tree/AvlTree.pxd
DataStructure/Tree/AvlTree.pyx
DataStructure/Tree/AvlTreeNode.c
DataStructure/Tree/AvlTreeNode.pxd
DataStructure/Tree/AvlTreeNode.pyx
DataStructure/Tree/BTree.c
DataStructure/Tree/BTree.pxd
DataStructure/Tree/BTree.pyx
DataStructure/Tree/BTreeNode.c
DataStructure/Tree/BTreeNode.pxd
DataStructure/Tree/BTreeNode.pyx
DataStructure/Tree/Tree.c
DataStructure/Tree/Tree.pxd
DataStructure/Tree/Tree.pyx
DataStructure/Tree/TreeNode.c
DataStructure/Tree/TreeNode.pxd
DataStructure/Tree/TreeNode.pyx
DataStructure/Tree/__init__.py
NlpToolkit_DataStructure_Cy.egg-info/PKG-INFO
NlpToolkit_DataStructure_Cy.egg-info/SOURCES.txt
NlpToolkit_DataStructure_Cy.egg-info/dependency_links.txt
NlpToolkit_DataStructure_Cy.egg-info/top_level.txt
nlpToolkit_datastructure_cy.egg-info/PKG-INFO
nlpToolkit_datastructure_cy.egg-info/SOURCES.txt
nlpToolkit_datastructure_cy.egg-info/dependency_links.txt
nlpToolkit_datastructure_cy.egg-info/top_level.txt