Metadata-Version: 2.4
Name: nlpToolkit-datastructure-cy
Version: 1.0.14
Summary: Simple Data Structures Library
Home-page: https://github.com/StarlangSoftware/DataStructure-Cy
Author: olcaytaner
Author-email: olcay.yildiz@ozyegin.edu.tr
License-File: LICENSE
Dynamic: author
Dynamic: author-email
Dynamic: description
Dynamic: description-content-type
Dynamic: home-page
Dynamic: license-file
Dynamic: summary
